microsoft/teams/cards/__init__.py
microsoft/teams/cards/core.py
microsoft/teams/cards/actions/__init__.py
microsoft/teams/cards/actions/im_back_action.py
microsoft/teams/cards/actions/invoke_action.py
microsoft/teams/cards/actions/message_back_action.py
microsoft/teams/cards/actions/sign_in_action.py
microsoft/teams/cards/actions/task_fetch_action.py
microsoft_teams_cards-2.0.0a5.dist-info/METADATA
microsoft_teams_cards-2.0.0a5.dist-info/WHEEL
microsoft_teams_cards-2.0.0a5.dist-info/RECORD
