Metadata-Version: 2.4
Name: microsoft-teams-cards
Version: 2.0.0a5
Summary: Cards package for Microsoft Teams
Project-URL: Homepage, https://github.com/microsoft/teams.py/tree/main/packages/cards/src/microsoft/teams/cards
Author-email: Microsoft <TeamsAISDKFeedback@microsoft.com>
License-Expression: MIT
Keywords: agents,ai,bot,microsoft,teams
Requires-Python: <3.14,>=3.12
Requires-Dist: coverage>=7.8.0
Requires-Dist: microsoft-teams-api
Requires-Dist: pytest>=8.3.5
Requires-Dist: ruff>=0.11.5
